trytond/modules/health_caldav/Changelog
trytond/modules/health_caldav/README.rst
trytond/modules/health_caldav/__init__.py
trytond/modules/health_caldav/caldav.py
trytond/modules/health_caldav/calendar.xml
trytond/modules/health_caldav/calendar_.py
trytond/modules/health_caldav/data/messages/messages.xml
trytond/modules/health_caldav/exceptions.py
trytond/modules/health_caldav/locale/ar.po
trytond/modules/health_caldav/locale/bg.po
trytond/modules/health_caldav/locale/cs.po
trytond/modules/health_caldav/locale/de.po
trytond/modules/health_caldav/locale/el.po
trytond/modules/health_caldav/locale/eo.po
trytond/modules/health_caldav/locale/es.po
trytond/modules/health_caldav/locale/fr.po
trytond/modules/health_caldav/locale/health_caldav.pot
trytond/modules/health_caldav/locale/it_IT.po
trytond/modules/health_caldav/locale/ja_JP.po
trytond/modules/health_caldav/locale/ka.po
trytond/modules/health_caldav/locale/lo.po
trytond/modules/health_caldav/locale/pt_BR.po
trytond/modules/health_caldav/locale/sv.po
trytond/modules/health_caldav/locale/tr.po
trytond/modules/health_caldav/locale/uk.po
trytond/modules/health_caldav/locale/zh_CN.po
trytond/modules/health_caldav/pyproject.toml
trytond/modules/health_caldav/res.py
trytond/modules/health_caldav/security/access_rights.xml
trytond/modules/health_caldav/tests/__init__.py
trytond/modules/health_caldav/tests/scenario_health_caldav.py
trytond/modules/health_caldav/tests/test_health_caldav.py
trytond/modules/health_caldav/tryton.cfg
trytond/modules/health_caldav/view/attendee_form.xml
trytond/modules/health_caldav/view/attendee_tree.xml
trytond/modules/health_caldav/view/calendar_form.xml
trytond/modules/health_caldav/view/calendar_tree.xml
trytond/modules/health_caldav/view/category_form.xml
trytond/modules/health_caldav/view/category_tree.xml
trytond/modules/health_caldav/view/event_form.xml
trytond/modules/health_caldav/view/event_tree.xml
trytond/modules/health_caldav/view/event_tree_occurence.xml
gnuhealth_caldav-5.0.2.dist-info/METADATA
gnuhealth_caldav-5.0.2.dist-info/WHEEL
gnuhealth_caldav-5.0.2.dist-info/RECORD
